.coveragerc
.gitignore
.readthedocs.yml
.travis.yml
LICENSE
LICENSE.txt
README.md
pyproject.toml
release.sh
setup.cfg
setup.py
setup.sh
tox.ini
src/yglu/__init__.py
src/yglu/builder.py
src/yglu/cli.py
src/yglu/dumper.py
src/yglu/expression.py
src/yglu/functions.py
src/yglu/loader.py
src/yglu/main.py
src/yglu/tree.py
src/yglu.egg-info/PKG-INFO
src/yglu.egg-info/SOURCES.txt
src/yglu.egg-info/dependency_links.txt
src/yglu.egg-info/entry_points.txt
src/yglu.egg-info/not-zip-safe
src/yglu.egg-info/requires.txt
src/yglu.egg-info/top_level.txt
tests/__init__.py
tests/conftest.py
tests/test_builder.py
tests/test_dumper.py
tests/test_errors.py
tests/test_expression.py
tests/test_functions.py
tests/test_main.py
tests/test_samples.py
tests/test_tree.py
tests/test_utils.py
tests/utils.py
tests/samples/environment.yml
tests/samples/expression.yml
tests/samples/for.yml
tests/samples/function-hierarchy.yml
tests/samples/function.yml
tests/samples/hidden.yml
tests/samples/if.yml
tests/samples/import.yml
tests/samples/imported.yaml
tests/samples/keys.yml
tests/samples/merge.yml
tests/samples/scope.yml
tests/samples/sequence-to-mapping.yml
tests/samples/strings.yml
tests/samples/kubernetes/ingress.yml
tests/samples/kubernetes/lib.yaml
tests/samples/kubernetes/values.yaml