Metadata-Version: 2.1
Name: yglu
Version: 1.1.1
Summary: YAML glue for structural templating and processing
Home-page: https://yglu.io
Author: Laurent Bovet
Author-email: laurent.bovet@windmaster.ch
License: MIT
Project-URL: Documentation, https://github.com/lbovet/yglu/blob/master.README.rst
Project-URL: Source, https://github.com/lbovet/yglu
Project-URL: Tracker, https://github.com/lbovet/yglu/issues
Platform: any
Classifier: Development Status :: 5 - Production/Stable
Classifier: License :: OSI Approved :: MIT License
Classifier: Programming Language :: Python :: 3
Classifier: Intended Audience :: Developers
Classifier: Topic :: Software Development :: Build Tools
Classifier: Operating System :: OS Independent
Requires-Python: >=3.6
Provides-Extra: testing
License-File: LICENSE
License-File: LICENSE.txt
